CHANGELOG.txt
LICENCE.txt
MANIFEST.in
README.txt
setup.py
jkhloufCalc.egg-info/SOURCES.txt
jkhloufCalc.egg-info/dependency_links.txt
jkhloufCalc.egg-info/top_level.txt
jkhloufCalculator.egg-info/PKG-INFO
jkhloufCalculator.egg-info/SOURCES.txt
jkhloufCalculator.egg-info/dependency_links.txt
jkhloufCalculator.egg-info/top_level.txt
jkhloufcalc/__init__.py